util_intelligence/__init__.py
util_intelligence/algorithm.py
util_intelligence/asynchronous.py
util_intelligence/blur.py
util_intelligence/char_util.py
util_intelligence/color.py
util_intelligence/context.py
util_intelligence/drawer.py
util_intelligence/environ.py
util_intelligence/func.py
util_intelligence/helper.py
util_intelligence/image_util.py
util_intelligence/io.py
util_intelligence/num_tiktoken.py
util_intelligence/pdfminer_helper.py
util_intelligence/py.typed
util_intelligence/regex.py
util_intelligence/report_util.py
util_intelligence/shape2d.py
util_intelligence/storage.py
util_intelligence/string_compare.py
util_intelligence/text_util.py
util_intelligence/timer.py
util_intelligence/block_data/__init__.py
util_intelligence/block_data/constants.py
util_intelligence/block_data/ocr_cut_overlapping.py
util_intelligence/block_data/table_block.py
util_intelligence/block_data/text_block.py
util_intelligence/block_data/types.py
util_intelligence/block_data/utils/__init__.py
util_intelligence/block_data/utils/algorithm.py
util_intelligence/block_data/utils/box_util.py
util_intelligence/model_interface/__init__.py
util_intelligence/model_interface/model_manager.py
util_intelligence/model_interface/pretrained_manager.py
util_intelligence-0.8.11.dist-info/licenses/LICENSE.txt
util_intelligence-0.8.11.dist-info/METADATA
util_intelligence-0.8.11.dist-info/WHEEL
util_intelligence-0.8.11.dist-info/top_level.txt
util_intelligence-0.8.11.dist-info/RECORD
