Metadata-Version: 2.4
Name: util_intelligence
Version: 0.8.11
Summary: ...
Author-email: Sheldon Lee <sheldonlee@outlook.com>
Classifier: Programming Language :: Python :: 3
Classifier: Operating System :: OS Independent
Requires-Python: >=3.8
License-File: LICENSE.txt
Provides-Extra: dev
Requires-Dist: pip; extra == "dev"
Requires-Dist: twine; extra == "dev"
Requires-Dist: build; extra == "dev"
Requires-Dist: pytest; extra == "dev"
Requires-Dist: mypy; extra == "dev"
Requires-Dist: types-Pillow; extra == "dev"
Requires-Dist: types-greenlet; extra == "dev"
Requires-Dist: lxml-stubs; extra == "dev"
Requires-Dist: types-python-dateutil; extra == "dev"
Requires-Dist: types-openpyxl; extra == "dev"
Dynamic: license-file
